rounded_calculate/__init__.py
rounded_calculate/calculator.py
rounded_calculate-0.1.1.dist-info/METADATA
rounded_calculate-0.1.1.dist-info/WHEEL
rounded_calculate-0.1.1.dist-info/licenses/LICENSE
rounded_calculate-0.1.1.dist-info/RECORD
