Metadata-Version: 2.1
Name: rounded_calculate
Version: 0.1.1
Summary: Rounded calculator package
Project-URL: Homepage, https://github.com/TuringCollegeSubmissions/vruzga-DWWP.1
Author-email: Vytautas Ruzgaila <DoNotContactMe@please.com>
License-File: LICENSE
Classifier: License :: OSI Approved :: MIT License
Classifier: Operating System :: OS Independent
Classifier: Programming Language :: Python :: 3
Requires-Python: >=3.7
